fortran_linter/__init__.py
fortran_linter/cli.py
fortran_linter/main.py
fortran_linter-1.1.3.dist-info/METADATA
fortran_linter-1.1.3.dist-info/WHEEL
fortran_linter-1.1.3.dist-info/entry_points.txt
fortran_linter-1.1.3.dist-info/licenses/LICENSE
fortran_linter-1.1.3.dist-info/RECORD
