Metadata-Version: 2.3
Name: fortran_linter
Version: 1.1.3
Summary: A linter for Fortran files
Project-URL: Homepage, https://github.com/cphyc/fortran-linter
Author-email: Corentin Cadiou <corentin.cadiou@iap.fr>
License: GPL
License-File: LICENSE
Keywords: fortran
Classifier: Development Status :: 4 - Beta
Classifier: Intended Audience :: Developers
Classifier: License :: OSI Approved :: GNU General Public License v2 or later (GPLv2+)
Classifier: Programming Language :: Fortran
Classifier: Topic :: Software Development :: Build Tools
Requires-Python: >=3.10
Provides-Extra: test
Requires-Dist: pytest; extra == 'test'
